README.rst
setup.cfg
setup.py
django_private_files_0.1.2.egg-info/PKG-INFO
django_private_files_0.1.2.egg-info/SOURCES.txt
django_private_files_0.1.2.egg-info/dependency_links.txt
django_private_files_0.1.2.egg-info/top_level.txt
private_files/__init__.py
private_files/signals.py
private_files/urls.py
private_files/views.py
private_files/models/__init__.py
private_files/models/fields.py