Metadata-Version: 1.1
Name: django-private-files-0.1.2
Version: 0.1.2
Summary: Protected files in django
Home-page: https://bitbucket.org/vvangelovski/django-private-files
Author: Vasil Vangelovski
Author-email: vvangelovski@gmail.com
License: New BSD License (http://www.opensource.org/licenses/bsd-license.php)
Download-URL: https://bitbucket.org/vvangelovski/django-private-files/downloads
Platform: UNKNOWN
Classifier: Development Status :: 3 - Alpha
Classifier: Environment :: Plugins
Classifier: Framework :: Django
Classifier: Intended Audience :: Developers
Classifier: License :: OSI Approved :: BSD License
Classifier: Topic :: Software Development :: Libraries :: Python Modules
